Metadata-Version: 2.1
Name: mlflow-stonewise
Version: 1.30.1
Summary: MLflow: A Platform for ML Development and Productionization
Home-page: https://mlflow.org/
Author: Databricks
Author-email: liuweibin@stonewise.cn
License: Apache License 2.0
Project-URL: Bug Tracker, https://github.com/mlflow/mlflow/issues
Project-URL: Documentation, https://mlflow.org/docs/latest/index.html
Project-URL: Source Code, https://github.com/mlflow/mlflow
Keywords: ml ai databricks
Classifier: Intended Audience :: Developers
Classifier: Programming Language :: Python :: 3.7
Requires-Python: >=3.7
License-File: LICENSE.txt
Requires-Dist: click (<9,>=7.0)
Requires-Dist: cloudpickle (<3)
Requires-Dist: databricks-cli (<1,>=0.8.7)
Requires-Dist: entrypoints (<1)
Requires-Dist: gitpython (<4,>=2.1.0)
Requires-Dist: pyyaml (<7,>=5.1)
Requires-Dist: protobuf (<5,>=3.12.0)
Requires-Dist: pytz (<2023)
Requires-Dist: requests (<3,>=2.17.3)
Requires-Dist: packaging (<22)
Requires-Dist: importlib-metadata (!=4.7.0,<6,>=3.7.0)
Requires-Dist: sqlparse (<1,>=0.4.0)
Requires-Dist: alembic (<2)
Requires-Dist: docker (<7,>=4.0.0)
Requires-Dist: Flask (<3)
Requires-Dist: numpy (<2)
Requires-Dist: scipy (<2)
Requires-Dist: pandas (<2)
Requires-Dist: prometheus-flask-exporter (<1)
Requires-Dist: querystring-parser (<2)
Requires-Dist: sqlalchemy (<2,>=1.4.0)
Requires-Dist: gunicorn (<21) ; platform_system != "Windows"
Requires-Dist: waitress (<3) ; platform_system == "Windows"
Provides-Extra: aliyun-oss
Requires-Dist: aliyunstoreplugin ; extra == 'aliyun-oss'
Provides-Extra: extras
Requires-Dist: scikit-learn ; extra == 'extras'
Requires-Dist: pyarrow ; extra == 'extras'
Requires-Dist: requests-auth-aws-sigv4 ; extra == 'extras'
Requires-Dist: boto3 ; extra == 'extras'
Requires-Dist: google-cloud-storage (>=1.30.0) ; extra == 'extras'
Requires-Dist: azureml-core (>=1.2.0) ; extra == 'extras'
Requires-Dist: pysftp ; extra == 'extras'
Requires-Dist: kubernetes ; extra == 'extras'
Requires-Dist: mlserver (>=0.5.3) ; extra == 'extras'
Requires-Dist: mlserver-mlflow (>=0.5.3) ; extra == 'extras'
Requires-Dist: virtualenv ; extra == 'extras'
Provides-Extra: pipelines
Requires-Dist: scikit-learn (>=1.0) ; extra == 'pipelines'
Requires-Dist: pyarrow (>=7.0) ; extra == 'pipelines'
Requires-Dist: shap (>=0.40) ; extra == 'pipelines'
Requires-Dist: pandas-profiling (>=3.1) ; extra == 'pipelines'
Requires-Dist: ipython (>=7.0) ; extra == 'pipelines'
Requires-Dist: markdown (>=3.3) ; extra == 'pipelines'
Requires-Dist: Jinja2 (>=2.11) ; (platform_system != "Windows") and extra == 'pipelines'
Requires-Dist: Jinja2 (>=3.0) ; (platform_system == "Windows") and extra == 'pipelines'
Provides-Extra: sqlserver
Requires-Dist: mlflow-dbstore ; extra == 'sqlserver'
